dwave_qbsolv/__init__.py
dwave_qbsolv/dimod_wrapper.py
dwave_qbsolv/qbsolv_binding.cpython-39-x86_64-linux-gnu.so
dwave_qbsolv-0.3.4.dist-info/LICENSE
dwave_qbsolv-0.3.4.dist-info/METADATA
dwave_qbsolv-0.3.4.dist-info/WHEEL
dwave_qbsolv-0.3.4.dist-info/top_level.txt
dwave_qbsolv-0.3.4.dist-info/RECORD
